lx_utils/__init__.py
lx_utils/__main__.py
lx_utils/date_handle.py
lx_utils/excel_handle.py
lx_utils/mongo_detect.py
lx_utils/mongo_handle.py
lx_utils/mq_detect.py
lx_utils/network_handle.py
lx_utils/port_detect.py
lx_utils/ssh_handle.py
lx_utils/weixin_alarm.py
lx_utils-0.0.5.dist-info/METADATA
lx_utils-0.0.5.dist-info/WHEEL
lx_utils-0.0.5.dist-info/entry_points.txt
lx_utils-0.0.5.dist-info/top_level.txt
lx_utils-0.0.5.dist-info/RECORD
